battleship_mp/__init__.py
battleship_mp/client.py
battleship_mp/exceptions.py
battleship_mp/messages.py
battleship_mp/server.py
kcsd_battleship_mp-1.1.0.dist-info/LICENSE
kcsd_battleship_mp-1.1.0.dist-info/METADATA
kcsd_battleship_mp-1.1.0.dist-info/WHEEL
kcsd_battleship_mp-1.1.0.dist-info/top_level.txt
kcsd_battleship_mp-1.1.0.dist-info/RECORD
