Metadata-Version: 2.1
Name: kcsd-battleship-mp
Version: 1.1.0
Summary: Multiplayer client/server for CSD BattleShip
Author-email: Max Fischer <max.fischer@kit.edu>
Project-URL: Homepage, https://github.com/kit-colsoftdes/battleship_mp
Project-URL: Bug Tracker, https://github.com/kit-colsoftdes/battleship_mp/issues
Classifier: Programming Language :: Python :: 3
Classifier: License :: OSI Approved :: MIT License
Classifier: Operating System :: OS Independent
Requires-Python: >=3.8
License-File: LICENSE
Requires-Dist: websockets
Provides-Extra: doc
Requires-Dist: sphinx ; extra == 'doc'
Provides-Extra: test
Requires-Dist: pytest ; extra == 'test'
Requires-Dist: pytest-cov ; extra == 'test'
Requires-Dist: flake8 ; extra == 'test'
Requires-Dist: flake8-bugbear ; extra == 'test'
Requires-Dist: black ; (implementation_name == "cpython") and extra == 'test'
Requires-Dist: mypy ; (implementation_name == "cpython") and extra == 'test'
